{
	"1358975": {
		"groupe": "101",
		"nom": "Arias",
		"prenom": "Camilo"
	},
	"1724388": {
		"groupe": "101",
		"nom": "Bisson",
		"prenom": "Edward"
	},
	"1842584": {
		"groupe": "101",
		"nom": "Couture",
		"prenom": "Ludérik"
	},
	"1408430": {
		"groupe": "101",
		"nom": "Daunais",
		"prenom": "Kevin"
	},
	"0688553": {
		"groupe": "101",
		"nom": "David",
		"prenom": "Jean-Samuel"
	},
	"1635094": {
		"groupe": "101",
		"nom": "Fouquet",
		"prenom": "Danyk"
	},
	"1829686": {
		"groupe": "101",
		"nom": "Galarneau",
		"prenom": "Jana"
	},
	"1839623": {
		"groupe": "101",
		"nom": "Gauthier-Robert",
		"prenom": "Sebastien-Junior"
	},
	"1775368": {
		"groupe": "101",
		"nom": "Golubyeva",
		"prenom": "Alona"
	},
	"1824715": {
		"groupe": "101",
		"nom": "Guillemette",
		"prenom": "Ann-Sophie"
	},
	"1693438": {
		"groupe": "101",
		"nom": "Labrecque",
		"prenom": "François"
	},
	"1863003": {
		"groupe": "101",
		"nom": "Le Blanc",
		"prenom": "Isabelle"
	},
	"1722086": {
		"groupe": "101",
		"nom": "Marras",
		"prenom": "Loïc"
	},
	"1586549": {
		"groupe": "101",
		"nom": "Morin",
		"prenom": "Gabriel"
	},
	"1834905": {
		"groupe": "101",
		"nom": "Morrisson",
		"prenom": "Samuel"
	},
	"1525605": {
		"groupe": "101",
		"nom": "Renaud",
		"prenom": "Tristan-William"
	},
	"1740582": {
		"groupe": "101",
		"nom": "Richard",
		"prenom": "Cédric"
	},
	"1821048": {
		"groupe": "101",
		"nom": "Rivard",
		"prenom": "Nathan"
	},
	"1851446": {
		"groupe": "101",
		"nom": "Séguin",
		"prenom": "Samuel"
	},
	"1836578": {
		"groupe": "101",
		"nom": "Smith",
		"prenom": "Vincent"
	},
	"1848124": {
		"groupe": "101",
		"nom": "St-Onge",
		"prenom": "Lukas"
	},
	"1873921": {
		"groupe": "101",
		"nom": "Verreault",
		"prenom": "Tristan"
	},
	"1839092": {
		"groupe": "102",
		"nom": "Bélanger",
		"prenom": "Gabriel"
	},
	"1802790": {
		"groupe": "102",
		"nom": "Coupal",
		"prenom": "Jeffrey"
	},
	"1642646": {
		"groupe": "102",
		"nom": "Gagnon",
		"prenom": "Olivier"
	},
	"1837465": {
		"groupe": "102",
		"nom": "Gauthier Fréchette",
		"prenom": "Myriam"
	},
	"1870631": {
		"groupe": "102",
		"nom": "Lauzon",
		"prenom": "Jagger"
	},
	"1829851": {
		"groupe": "102",
		"nom": "Lavoie",
		"prenom": "Benjamin"
	},
	"1848198": {
		"groupe": "102",
		"nom": "Leblond",
		"prenom": "Jérémie"
	},
	"1138297": {
		"groupe": "102",
		"nom": "Lopes",
		"prenom": "Marie-Elaine"
	},
	"1645842": {
		"groupe": "102",
		"nom": "Makin-Leblanc",
		"prenom": "Joey"
	},
	"1726639": {
		"groupe": "102",
		"nom": "Morissette",
		"prenom": "Ariel"
	},
	"1724269": {
		"groupe": "102",
		"nom": "Prévost-Desrosiers",
		"prenom": "Amélie"
	},
	"1604765": {
		"groupe": "102",
		"nom": "Rousseau",
		"prenom": "Frédéric"
	},
	"1540437": {
		"groupe": "102",
		"nom": "St-Pierre",
		"prenom": "Thomas"
	},
	"1836149": {
		"groupe": "102",
		"nom": "Thierry",
		"prenom": "Pierrick"
	},
	"1830250": {
		"groupe": "103",
		"nom": "Arsenault",
		"prenom": "Molly"
	},
	"1849037": {
		"groupe": "103",
		"nom": "Beaudet",
		"prenom": "Kory"
	},
	"1836393": {
		"groupe": "103",
		"nom": "Bravo Perez",
		"prenom": "Natalia"
	},
	"1871061": {
		"groupe": "103",
		"nom": "Chabot",
		"prenom": "Vincent"
	},
	"1826905": {
		"groupe": "103",
		"nom": "Coupal",
		"prenom": "Léa"
	},
	"1881919": {
		"groupe": "103",
		"nom": "De la Durantaye",
		"prenom": "Rémi"
	},
	"1727313": {
		"groupe": "103",
		"nom": "Dufort",
		"prenom": "Laurie"
	},
	"1809926": {
		"groupe": "103",
		"nom": "Fournier",
		"prenom": "Gabriel"
	},
	"1837491": {
		"groupe": "103",
		"nom": "Gauthier Fréchette",
		"prenom": "Audrey"
	},
	"1756274": {
		"groupe": "103",
		"nom": "Lalumière",
		"prenom": "Mylène"
	},
	"1853004": {
		"groupe": "103",
		"nom": "Lamoureux",
		"prenom": "William"
	},
	"1811776": {
		"groupe": "103",
		"nom": "Langlois",
		"prenom": "David"
	},
	"1765248": {
		"groupe": "103",
		"nom": "Laramée",
		"prenom": "Sébastien"
	},
	"1846894": {
		"groupe": "103",
		"nom": "Leon",
		"prenom": "Adrian"
	},
	"1848260": {
		"groupe": "103",
		"nom": "Lynch",
		"prenom": "Samuel"
	},
	"1383532": {
		"groupe": "103",
		"nom": "Paquette",
		"prenom": "Gabriel R."
	},
	"1804012": {
		"groupe": "103",
		"nom": "Richer",
		"prenom": "Félix"
	},
	"1823863": {
		"groupe": "103",
		"nom": "Soucy Langlois",
		"prenom": "Christopher"
	},
	"1865637": {
		"groupe": "103",
		"nom": "St-Laurent",
		"prenom": "Jacob"
	},
	"1874418": {
		"groupe": "103",
		"nom": "St-Pierre",
		"prenom": "Alexis"
	},
	"1755036": {
		"groupe": "104",
		"nom": "Arroub",
		"prenom": "Zakaria"
	},
	"1873554": {
		"groupe": "104",
		"nom": "Auger",
		"prenom": "Mickael"
	},
	"1833787": {
		"groupe": "104",
		"nom": "Barrette",
		"prenom": "Edouard"
	},
	"1549530": {
		"groupe": "104",
		"nom": "Charbonneau",
		"prenom": "Noémie"
	},
	"1814737": {
		"groupe": "104",
		"nom": "Deguire",
		"prenom": "Yoann"
	},
	"6130775": {
		"groupe": "104",
		"nom": "Forero-Bulnes",
		"prenom": "Alexis"
	},
	"1851281": {
		"groupe": "104",
		"nom": "Giroux",
		"prenom": "Jimmy"
	},
	"1837660": {
		"groupe": "104",
		"nom": "Labre",
		"prenom": "Jessica"
	},
	"9031826": {
		"groupe": "104",
		"nom": "Landry",
		"prenom": "Catherine"
	},
	"1120829": {
		"groupe": "104",
		"nom": "Laroche",
		"prenom": "Myriam"
	},
	"1720678": {
		"groupe": "104",
		"nom": "Larochelle",
		"prenom": "Leila"
	},
	"1855303": {
		"groupe": "104",
		"nom": "Legendre",
		"prenom": "Simon"
	},
	"1874438": {
		"groupe": "104",
		"nom": "Lemieux",
		"prenom": "Lukas"
	},
	"1847849": {
		"groupe": "104",
		"nom": "Plamondon",
		"prenom": "Olivier"
	},
	"1841453": {
		"groupe": "104",
		"nom": "Plante",
		"prenom": "Nicolas"
	},
	"1724935": {
		"groupe": "104",
		"nom": "Prud'Homme",
		"prenom": "Marilou"
	},
	"1862325": {
		"groupe": "104",
		"nom": "Repeta",
		"prenom": "Emanuelle"
	},
	"1831692": {
		"groupe": "104",
		"nom": "St-Jean",
		"prenom": "Félix"
	}
}
