{
	"titre": "Exemple|droite",
	"colonnes": 4,
	"rangees": 1,
	"colonnesInternes": 1,
	"valeur": null,
	"papier": "legal",
	"orientation": "paysage",
	"police": 12,
	"trou": 18,
	"criteres": [
		{
			"titre": "Un critère avec sous-critères",
			"criteres": [
				{
					"titre": "Premier sous-critère",
					"valeur": 3
				},
				{
					"titre": "Deuxième sous-critère sans valeur"				},
				{
					"titre": "Et des sous-sous-critères",
					"criteres": [
						{
							"titre": "Un sous-sous-critère",
							"valeur": 3
						}
					]
				}
			]
		},
		{
			"titre": "Un critère sans sous-critère",
			"valeur": 3
			
		},
		{
			"titre": "Des commentaires",
			"lignes": 5
		}
	]
}
